fgarcade/__init__.py
fgarcade/assets.py
fgarcade/enums.py
fgarcade/fix.py
fgarcade/level_factory.py
fgarcade/physics.py
fgarcade/platformer.py
fgarcade/sprites.py
fgarcade/utils.py
fgarcade/data/fonts/monogram_extended.ttf
fgarcade/data/themes/abstract/license.txt
fgarcade/data/themes/abstract/sample.png
fgarcade/data/themes/abstract/background/blue/background.png
fgarcade/data/themes/abstract/background/blue/hills.png
fgarcade/data/themes/abstract/background/blue/tiles.png
fgarcade/data/themes/abstract/background/brown/background.png
fgarcade/data/themes/abstract/background/brown/hills.png
fgarcade/data/themes/abstract/background/brown/tiles.png
fgarcade/data/themes/abstract/background/green/background.png
fgarcade/data/themes/abstract/background/green/hills.png
fgarcade/data/themes/abstract/background/green/tiles.png
fgarcade/data/themes/abstract/background/yellow/background.png
fgarcade/data/themes/abstract/background/yellow/hills.png
fgarcade/data/themes/abstract/background/yellow/tiles.png
fgarcade/data/themes/abstract/enemy/enemyFloating_1.png
fgarcade/data/themes/abstract/enemy/enemyFloating_2.png
fgarcade/data/themes/abstract/enemy/enemyFloating_3.png
fgarcade/data/themes/abstract/enemy/enemyFloating_4.png
fgarcade/data/themes/abstract/enemy/enemyFlyingAlt_1.png
fgarcade/data/themes/abstract/enemy/enemyFlyingAlt_2.png
fgarcade/data/themes/abstract/enemy/enemyFlyingAlt_3.png
fgarcade/data/themes/abstract/enemy/enemyFlyingAlt_4.png
fgarcade/data/themes/abstract/enemy/enemyFlying_1.png
fgarcade/data/themes/abstract/enemy/enemyFlying_2.png
fgarcade/data/themes/abstract/enemy/enemyFlying_3.png
fgarcade/data/themes/abstract/enemy/enemyFlying_4.png
fgarcade/data/themes/abstract/enemy/enemySpikey_1.png
fgarcade/data/themes/abstract/enemy/enemySpikey_2.png
fgarcade/data/themes/abstract/enemy/enemySpikey_3.png
fgarcade/data/themes/abstract/enemy/enemySpikey_4.png
fgarcade/data/themes/abstract/enemy/enemySwimming_1.png
fgarcade-0.1.1.dist-info/LICENSE
fgarcade-0.1.1.dist-info/WHEEL
fgarcade-0.1.1.dist-info/METADATA
fgarcade-0.1.1.dist-info/RECORD
