Metadata-Version: 2.1
Name: fgarcade
Version: 0.1.1
Summary: FGA + Arcade: A simple abstraction on top of the Arcade library to easily create
Home-page: http://github.com/fabiommendes/fgarcade/
License: UNKNOWN
Author: Fábio Macêdo Mendes
Author-email: fabiomacedomendes@gmail.com
Classifier: License :: OSI Approved :: MIT License
Requires-Dist: arcade~=2.0.9
Requires-Dist: toolz
Requires-Dist: sidekick
